{
  "url": "https://api.namefake.com/english-united-states/female/f6bf697d3fc9400babefc1f83ce1df0e",
  "eye": "Blue",
  "domain": "hermann.com",
  "name": "Flavie Jones IV",
  "email_url": "//emailfake.com/gmailvn.net/liliana89",
  "height": 192,
  "sport": "Volleyball",
  "ipv4_url": "//myip-address.com/ip-lookup/46.100.117.193",
  "weight": 105.6,
  "ipv4": "46.100.117.193",
  "password": "}XS'f]a+YL",
  "username": "cweissnat",
  "domain_url": "//myip-address.com/ip-lookup/hermann.com",
  "email_u": "liliana89",
  "color": "silver",
  "cardexpir": "10/23",
  "address": "836 Bruen Locks Apt. 925\nNew Else, AK 62370-5085",
  "blood": "O−",
  "phone_h": "(359)858-1588",
  "uuid": "8987cba5-3f8e-3d4a-9a84-b8ec09f0980c",
  "useragent": "Mozilla/5.0 (iPhone; CPU iPhone OS 8_2_2 like Mac OS X; en-US) AppleWebKit/532.12.3 (KHTML, like Gecko) Version/3.0.5 Mobile/8B112 Safari/6532.12.3",
  "email_d": "gmailvn.net",
  "company": "Stamm-Orn",
  "birth_data": "1986-04-23",
  "bonus": 29,
  "macaddress": "D5:EF:38:E1:B9:D5",
  "plasticcard": "5579217226803476",
  "longitude": 24.499212999999997,
  "latitude": 2.3082780000000014,
  "pict": "2female",
  "phone_w": "576.534.7262x9232",
  "hair": "Wavy, Brown",
  "maiden_name": "Towne"
}
