{
  "url": "https://api.namefake.com/english-united-states/male/2419061c5fda24f8602a899fd4ba00ec",
  "eye": "Gray",
  "domain": "hackett.com",
  "name": "Dr. Garrick Ankunding IV",
  "email_url": "//emailfake.com/roidirt.com/brennan67",
  "height": 157,
  "sport": "Boxing",
  "ipv4_url": "//myip-address.com/ip-lookup/142.167.185.239",
  "weight": 48,
  "ipv4": "142.167.185.239",
  "password": "\\Vt,bbQN4{.mo7",
  "username": "jimmynolan",
  "domain_url": "//myip-address.com/ip-lookup/hackett.com",
  "email_u": "brennan67",
  "color": "purple",
  "cardexpir": "09/22",
  "address": "2504 Harvey Throughway Apt. 458\nWest Brenna, AK 56908-6657",
  "blood": "O+",
  "phone_h": "1-094-951-5834x00985",
  "uuid": "968e9e11-7146-330d-b614-ae7516e48ae0",
  "useragent": "Mozilla/5.0 (Windows; U; Windows NT 6.2) AppleWebKit/534.3.7 (KHTML, like Gecko) Version/4.0 Safari/534.3.7",
  "email_d": "roidirt.com",
  "company": "Dibbert, Lubowitz and Herzog",
  "birth_data": "1988-11-29",
  "bonus": 9,
  "macaddress": "E4:C4:D5:F1:36:34",
  "plasticcard": "4539204930784533",
  "longitude": 129.00177300000001,
  "gpa": 0,
  "latitude": 78.203453,
  "pict": "8male",
  "phone_w": "(173)549-2629",
  "hair": "Very curly, Black",
  "maiden_name": "Dibbert"
}
